{
    "ShouldReturnIdsFromThirdBatchIfSecondBatchTakenByAnotherGenerator": [
        "Container_Create",
        "Blob_GetProperties",
        "BlockBlob_Upload",
        "Blob_Download",
        "Container_Delete"
    ],
    "ShouldNotUpdateBlobAtEndOfBatch": [
        "Container_Create",
        "Blob_GetProperties",
        "BlockBlob_Upload",
        "Blob_Download",
        "Container_Delete"
    ],
    "ShouldUpdateBlobWhenGeneratingNextIdAfterEndOfBatch": [
        "Container_Create",
        "Blob_GetProperties",
        "BlockBlob_Upload",
        "Blob_Download",
        "Container_Delete"
    ],
    "ShouldSupportUsingOneGeneratorFromMultipleThreads": [
        "Container_Create",
        "Blob_GetProperties",
        "BlockBlob_Upload",
        "Blob_Download",
        "Container_Delete"
    ],
    "ShouldReturnOneForFirstIdInNewScope": [
        "Container_Create",
        "Blob_GetProperties",
        "BlockBlob_Upload",
        "Blob_Download",
        "Container_Delete"
    ],
    "ShouldInitializeBlobForFirstIdInNewScope": [
        "Container_Create",
        "Blob_GetProperties",
        "BlockBlob_Upload",
        "Blob_Download",
        "Container_Delete"
    ],
    "ShouldReturnIdsAcrossMultipleGenerators": [
        "Container_Create",
        "Blob_GetProperties",
        "BlockBlob_Upload",
        "Blob_Download",
        "Container_Delete"
    ]
}